yt_dlp_plugins/extractor/radiko.py
yt_dlp_plugins/extractor/radiko_aSmartPhone7a.bin
yt_dlp_plugins/extractor/radiko_dependencies.py
yt_dlp_plugins/extractor/radiko_hacks.py
yt_dlp_plugins/extractor/radiko_podcast.py
yt_dlp_plugins/extractor/radiko_protobufs.py
yt_dlp_plugins/extractor/radiko_time.py
yt_dlp_rajiko-1.10.dist-info/licenses/LICENCE
yt_dlp_rajiko-1.10.dist-info/METADATA
yt_dlp_rajiko-1.10.dist-info/WHEEL
yt_dlp_rajiko-1.10.dist-info/top_level.txt
yt_dlp_rajiko-1.10.dist-info/RECORD
