Metadata-Version: 2.4
Name: yt-dlp-rajiko
Version: 1.10
Summary: improved radiko.jp extractor for yt-dlp (fast and areafree)
Author: garret1317
License-Expression: 0BSD
Project-URL: Homepage, https://427738.xyz/yt-dlp-rajiko/
Project-URL: 日本語, https://427738.xyz/yt-dlp-rajiko/index.ja.html
Project-URL: Source Code, https://github.com/garret1317/yt-dlp-rajiko/
Project-URL: Release Notes, https://427738.xyz/yt-dlp-rajiko/CHANGELOG.xml
Classifier: Environment :: Plugins
Requires-Python: >=3.8
License-File: LICENCE
Requires-Dist: protobug
Dynamic: license-file
